{
  "@midwayjs/faas-typings": "3.6.0",
  "@midwayjs/fc-starter": "3.9.0",
  "@midwayjs/serverless-http-parser": "3.6.0",
  "@midwayjs/async-hooks-context-manager": "3.9.0",
  "@midwayjs/axios": "3.9.0",
  "@midwayjs/bootstrap": [
    "3.9.0",
    "3.9.1"
  ],
  "@midwayjs/bull-board": [
    "3.9.0",
    "3.9.2",
    "3.9.7",
    "3.9.9"
  ],
  "@midwayjs/bull": [
    "3.9.0",
    "3.9.2",
    "3.9.7"
  ],
  "@midwayjs/cache": "3.9.0",
  "@midwayjs/captcha": [
    "3.9.0",
    "3.9.9"
  ],
  "@midwayjs/casbin-redis-adapter": [
    "3.9.0",
    "3.9.9"
  ],
  "@midwayjs/casbin-typeorm-adapter": [
    "3.9.0",
    "3.9.3",
    "3.9.4",
    "3.9.5",
    "3.9.9"
  ],
  "@midwayjs/casbin": [
    "3.9.0",
    "3.9.9"
  ],
  "@midwayjs/code-dye": [
    "3.9.0",
    "3.9.1",
    "3.9.9"
  ],
  "@midwayjs/consul": [
    "3.9.0",
    "3.9.9"
  ],
  "@midwayjs/core": "3.9.0",
  "@midwayjs/cos": "3.9.0",
  "@midwayjs/cross-domain": [
    "3.9.0",
    "3.9.1",
    "3.9.6",
    "3.9.9"
  ],
  "@midwayjs/decorator": "3.9.0",
  "@midwayjs/etcd": "3.9.0",
  "@midwayjs/express-session": "3.9.0",
  "@midwayjs/faas": "3.9.0",
  "@midwayjs/grpc": "3.9.0",
  "@midwayjs/http-proxy": [
    "3.9.0",
    "3.9.1",
    "3.9.6",
    "3.9.9"
  ],
  "@midwayjs/i18n": [
    "3.9.0",
    "3.9.9"
  ],
  "@midwayjs/info": [
    "3.9.0",
    "3.9.9"
  ],
  "@midwayjs/jwt": [
    "3.9.0",
    "3.9.9"
  ],
  "@midwayjs/kafka": "3.9.0",
  "@midwayjs/mikro": "3.9.0",
  "@midwayjs/mock": "3.9.0",
  "@midwayjs/mongoose": "3.9.0",
  "@midwayjs/oss": "3.9.0",
  "@midwayjs/otel": [
    "3.9.0",
    "3.9.9"
  ],
  "@midwayjs/passport": [
    "3.9.0",
    "3.9.9"
  ],
  "@midwayjs/process-agent": [
    "3.9.0",
    "3.9.9"
  ],
  "@midwayjs/prometheus-socket-io": [
    "3.9.0",
    "3.9.9"
  ],
  "@midwayjs/prometheus": [
    "3.9.0",
    "3.9.9"
  ],
  "@midwayjs/rabbitmq": "3.9.0",
  "@midwayjs/redis": "3.9.0",
  "@midwayjs/security": [
    "3.9.0",
    "3.9.1",
    "3.9.9"
  ],
  "@midwayjs/sequelize": [
    "3.9.0",
    "3.9.9"
  ],
  "@midwayjs/session": "3.9.0",
  "@midwayjs/socketio": "3.9.0",
  "@midwayjs/static-file": [
    "3.9.0",
    "3.9.1",
    "3.9.6",
    "3.9.9"
  ],
  "@midwayjs/swagger": [
    "3.9.0",
    "3.9.3",
    "3.9.8",
    "3.9.9"
  ],
  "@midwayjs/tablestore": "3.9.0",
  "@midwayjs/typegoose": "3.9.0",
  "@midwayjs/typeorm": [
    "3.9.0",
    "3.9.3",
    "3.9.4",
    "3.9.5"
  ],
  "@midwayjs/upload": [
    "3.9.0",
    "3.9.1",
    "3.9.9"
  ],
  "@midwayjs/validate": [
    "3.9.0",
    "3.9.9"
  ],
  "@midwayjs/version": [
    "3.9.0",
    "3.9.1",
    "3.9.2",
    "3.9.3",
    "3.9.4",
    "3.9.5",
    "3.9.6",
    "3.9.7",
    "3.9.8",
    "3.9.9"
  ],
  "@midwayjs/view-ejs": [
    "3.9.0",
    "3.9.9"
  ],
  "@midwayjs/view-nunjucks": [
    "3.9.0",
    "3.9.9"
  ],
  "@midwayjs/view": [
    "3.9.0",
    "3.9.9"
  ],
  "@midwayjs/express": [
    "3.9.0",
    "3.9.9"
  ],
  "@midwayjs/koa": [
    "3.9.0",
    "3.9.9"
  ],
  "@midwayjs/web": [
    "3.9.0",
    "3.9.9"
  ],
  "@midwayjs/ws": "3.9.0"
}